Workbook

Sheet Resumen y Diagnostico
A1: DIAGNÓSTICO INTEGRAL Y ALINEACIÓN VOCACIONAL
A2: Licenciatura en Administración - 5º Semestre | Cruce de Habilidades Percibidas y Personalidad Big Five
A4: Nombre del Alumno: | B4: [Nombre Completo del Estudiante] | E4: Matrícula / Grupo: | F4: [Matrícula - 5º A]
A6: 1. MATRIZ DE COMPATIBILIDAD POR CAMPO FORMATIVO (CRUCE DE EVALUACIONES)
A7: Campo Formativo (Especialidad) | B7: Puntaje Habilidad (0-20) | C7: % Habilidad | D7: Perfil OCEAN Requerido | E7: % Personalidad (Big Five) | F7: Índice Global de Compatibilidad | G7: Nivel de Alineación
A8: Mercadotecnia (M) | B8: ='Test 1 - Habilidades'!F9 -> 16 | C8: =B8/20 -> 0.8 | D8: Alta Apertura + Alta Extraversión | E8: ='Test 2 - Big Five'!F9*0.5 + 'Test 2 - Big Five'!F19*0.5 -> 0.8 | F8: =C8*0.5 + E8*0.5 -> 0.8 | G8: =IF(F8>=0.8,"Alta Compatibilidad",IF(F8>=0.65,"Compatibilidad Media","Baja Compatibilidad")) -> Alta Compatibilidad
A9: Capital Humano (CH) | B9: ='Test 1 - Habilidades'!F14 -> 17 | C9: =B9/20 -> 0.85 | D9: Alta Amabilidad + Alta Extraversión | E9: ='Test 2 - Big Five'!F24*0.5 + 'Test 2 - Big Five'!F19*0.5 -> 0.8 | F9: =C9*0.5 + E9*0.5 -> 0.825 | G9: =IF(F9>=0.8,"Alta Compatibilidad",IF(F9>=0.65,"Compatibilidad Media","Baja Compatibilidad")) -> Alta Compatibilidad
A10: Administración Financiera (AF) | B10: ='Test 1 - Habilidades'!F19 -> 13 | C10: =B10/20 -> 0.65 | D10: Alta Responsabilidad + Alta Estabilidad | E10: ='Test 2 - Big Five'!F14*0.5 + 'Test 2 - Big Five'!F29*0.5 -> 0.74 | F10: =C10*0.5 + E10*0.5 -> 0.695 | G10: =IF(F10>=0.8,"Alta Compatibilidad",IF(F10>=0.65,"Compatibilidad Media","Baja Compatibilidad")) -> Compatibilidad Media
A11: Negocios Internacionales (NI) | B11: ='Test 1 - Habilidades'!F24 -> 13 | C11: =B11/20 -> 0.65 | D11: Alta Apertura + Estabilidad + Extraversión | E11: ='Test 2 - Big Five'!F9*0.4 + 'Test 2 - Big Five'!F29*0.3 + 'Test 2 - Big Five'!F19*0.3 -> 0.776 | F11: =C11*0.5 + E11*0.5 -> 0.713 | G11: =IF(F11>=0.8,"Alta Compatibilidad",IF(F11>=0.65,"Compatibilidad Media","Baja Compatibilidad")) -> Compatibilidad Media
A12: Emprendimiento (E) | B12: ='Test 1 - Habilidades'!F29 -> 16 | C12: =B12/20 -> 0.8 | D12: Alta Apertura + Responsabilidad + Estabilidad | E12: ='Test 2 - Big Five'!F9*0.4 + 'Test 2 - Big Five'!F14*0.3 + 'Test 2 - Big Five'!F29*0.3 -> 0.764 | F12: =C12*0.5 + E12*0.5 -> 0.782 | G12: =IF(F12>=0.8,"Alta Compatibilidad",IF(F12>=0.65,"Compatibilidad Media","Baja Compatibilidad")) -> Compatibilidad Media
A31: 2. RESULTADO DIAGNÓSTICO Y SELECCIÓN AUTOMÁTICA DE ESPECIALIDAD
A33: 1ª Opción Recomendada (Máxima Afinidad): | C33: =INDEX(A8:A12, MATCH(MAX(F8:F12), F8:F12, 0)) -> Capital Humano (CH) | E33: Índice de Afinidad: | F33: =MAX(F8:F12) -> 0.825
A34: ="INTERPRETACIÓN AUTOMÁTICA: El alumno presenta su mayor nivel de compatibilidad en " & INDEX(A8:A12, MATCH(MAX(F8:F12), F8:F12, 0)) & " con un " & TEXT(MAX(F8:F12),"0.0%") & " de alineación global. Este campo representa la combinación óptima entre su dominio técnico/autonomía percibida y sus rasgos naturales de personalidad." -> INTERPRETACIÓN AUTOMÁTICA: El alumno presenta su mayor nivel de compatibilidad en Capital Humano (CH) con un 82.5% de alineación global. Este campo representa la combinación óptima entre su dominio técnico/autonomía percibida y sus rasgos naturales de personalidad.
A36: 2ª Opción Recomendada (Secundaria): | C36: =INDEX(A8:A12, MATCH(LARGE(F8:F12, 2), F8:F12, 0)) -> Mercadotecnia (M) | E36: Índice de Afinidad: | F36: =LARGE(F8:F12, 2) -> 0.8
A37: ="INTERPRETACIÓN AUTOMÁTICA: La especialidad de respaldo recomendada es " & INDEX(A8:A12, MATCH(LARGE(F8:F12, 2), F8:F12, 0)) & " (" & TEXT(LARGE(F8:F12, 2),"0.0%") & "). Constituye una excelente opción de diversificación profesional alineada con sus competencias secundarias." -> INTERPRETACIÓN AUTOMÁTICA: La especialidad de respaldo recomendada es Mercadotecnia (M) (80.0%). Constituye una excelente opción de diversificación profesional alineada con sus competencias secundarias.
A40: 3. GUÍA DE INTERPRETACIÓN DETALLADA Y ANÁLISIS DE BRECHAS
A41: Mercadotecnia (M) | B41: Requiere alta Apertura (creatividad, innovación) y Extraversión (comunicación persuasiva). Un puntaje elevado indica facultad natural para investigación de mercados, gestión de marca y estrategias digitales.
A42: Capital Humano (CH) | B42: Demanda elevada Amabilidad (empatía, resolución pacífica) y Extraversión (liderazgo). Apto para la gestión del talento, desarrollo organizacional, negociación laboral y clima de trabajo.
A43: Administración Financiera (AF) | B43: Se fundamenta en alta Responsabilidad (rigor, meticulosidad) y Estabilidad Emocional (aplomo bajo riesgo). Ideal para presupuestos, evaluación de inversiones y control financiero.
A44: Negocios Internacionales (NI) | B44: Combina Apertura cultural, Estabilidad emocional y Extraversión. Excelente perfil para comercio exterior, logística global, negociación intercultural y expansión internacional.
A45: Emprendimiento (E) | B45: Exige elevada Apertura (visión de oportunidad), Responsabilidad (ejecución) y Estabilidad (resiliencia ante fallas). Adecuado para diseño de modelos de negocio Canvas y pilotaje de startups.
A47: ANÁLISIS DE BRECHAS Y ORIENTACIÓN PARA EL ESTUDIANTE:
A48: • Alta Personalidad + Baja Habilidad: Indica un 'potencial latente'. El estudiante posee la inclinación natural pero requiere formación técnica en 5º-8º semestre para elevar su autonomía práctica.
A49: • Alta Habilidad + Baja Personalidad: Señala un 'desempeño técnico disciplinado'. El alumno ejecuta con precisión pero requerirá autorregulación consciente para evitar el desgaste en esa área.
A50: • Nota clave del modelo Big Five: La personalidad no es una limitante rígida, sino una guía de autoconocimiento para desarrollar conscientemente las competencias necesarias para la especialidad deseada.

Sheet Test 1 - Habilidades
A1: EVALUACIÓN DE HABILIDADES PERCIBIDAS EN ADMINISTRACIÓN (TEST 1)
A2: Escala de Autonomía: 0 = Necesito ayuda total | 1 = Con supervisión directa | 2 = Con orientación ocasional | 3 = De forma autónoma | 4 = De forma autónoma y puedo explicarlo a otros
A4: No. | B4: Campo Formativo / Reactivo de Conducta Observable | C4: Autonomía (0-4) | D4: Nivel Esperado | E4: Especialidad | F4: Subtotal Campo | G4: Estado Campo
A5: 1 | B5: Identificar patrones de consumo y necesidades del cliente objetivo | C5: 3 | D5: Dominio (3-4) | E5: Mercadotecnia (M)
A6: 2 | B6: Seleccionar canales digitales y tradicionales de comunicación persuasiva | C6: 4 | D6: Dominio (3-4) | E6: Mercadotecnia (M)
A7: 3 | B7: Diseñar y adaptar mensajes publicitarios según el público segmento | C7: 3 | D7: Dominio (3-4) | E7: Mercadotecnia (M)
A8: 4 | B8: Analizar la competencia y definir propuestas de valor diferenciadoras | C8: 3 | D8: Dominio (3-4) | E8: Mercadotecnia (M)
A9: 5 | B9: Evaluar el impacto de campañas comerciales mediante métricas básicas | C9: 3 | D9: Dominio (3-4) | E9: Mercadotecnia (M) | F9: =SUM(C5:C9) -> 16 | G9: =IF(F9>=16,"Alto (16-20)",IF(F9>=11,"Medio (11-15)","Bajo (0-10)")) -> Alto (16-20)
A10: 6 | B10: Escuchar de forma empática las inquietudes del personal en un equipo | C10: 4 | D10: Dominio (3-4) | E10: Capital Humano (CH)
A11: 7 | B11: Asignar tareas considerando las fortalezas individuales de los colaboradores | C11: 3 | D11: Dominio (3-4) | E11: Capital Humano (CH)
A12: 8 | B12: Brindar retroalimentación constructiva para mejorar el desempeño | C12: 3 | D12: Dominio (3-4) | E12: Capital Humano (CH)
A13: 9 | B13: Resolver malentendidos y mediaciones grupales de forma pacífica | C13: 3 | D13: Dominio (3-4) | E13: Capital Humano (CH)
A14: 10 | B14: Fomentar un clima de trabajo colaborativo y de respeto mutuo | C14: 4 | D14: Dominio (3-4) | E14: Capital Humano (CH) | F14: =SUM(C10:C14) -> 17 | G14: =IF(F14>=16,"Alto (16-20)",IF(F14>=11,"Medio (11-15)","Bajo (0-10)")) -> Alto (16-20)
A15: 11 | B15: Clasificar ingresos, costos y gastos operativos de una unidad administrativa | C15: 3 | D15: Dominio (3-4) | E15: Administración Financiera (AF)
A16: 12 | B16: Realizar cálculos numéricos y porcentuales para presupuestos sencillos | C16: 3 | D16: Dominio (3-4) | E16: Administración Financiera (AF)
A17: 13 | B17: Elaborar proyecciones financieras básicas a corto y mediano plazo | C17: 2 | D17: Dominio (3-4) | E17: Administración Financiera (AF)
A18: 14 | B18: Evaluar la relación costo-beneficio de una inversión o proyecto | C18: 3 | D18: Dominio (3-4) | E18: Administración Financiera (AF)
A19: 15 | B19: Interpretar estados de resultados para la toma de decisiones presupuestales | C19: 2 | D19: Dominio (3-4) | E19: Administración Financiera (AF) | F19: =SUM(C15:C19) -> 13 | G19: =IF(F19>=16,"Alto (16-20)",IF(F19>=11,"Medio (11-15)","Bajo (0-10)")) -> Medio (11-15)
A20: 16 | B20: Comunicarse adecuadamente con personas de diferentes contextos culturales | C20: 3 | D20: Dominio (3-4) | E20: Negocios Internacionales (NI)
A21: 17 | B21: Investigar regulaciones aduaneras y trámites de comercio exterior | C21: 2 | D21: Dominio (3-4) | E21: Negocios Internacionales (NI)
A22: 18 | B22: Analizar el impacto de divisas y tendencias del mercado internacional | C22: 3 | D22: Dominio (3-4) | E22: Negocios Internacionales (NI)
A23: 19 | B23: Identificar oportunidades de expansión o alianzas estratégicas globales | C23: 3 | D23: Dominio (3-4) | E23: Negocios Internacionales (NI)
A24: 20 | B24: Adaptar productos o servicios a estándares y normas internacionales | C24: 2 | D24: Dominio (3-4) | E24: Negocios Internacionales (NI) | F24: =SUM(C20:C24) -> 13 | G24: =IF(F24>=16,"Alto (16-20)",IF(F24>=11,"Medio (11-15)","Bajo (0-10)")) -> Medio (11-15)
A25: 21 | B25: Identificar oportunidades de negocio a partir de problemas cotidianos | C25: 4 | D25: Dominio (3-4) | E25: Emprendimiento (E)
A26: 22 | B26: Diseñar prototipos o pruebas piloto para validar ideas innovadoras | C26: 3 | D26: Dominio (3-4) | E26: Emprendimiento (E)
A27: 23 | B27: Establecer planes de acción flexibles que se adapten a la incertidumbre | C27: 3 | D27: Dominio (3-4) | E27: Emprendimiento (E)
A28: 24 | B28: Movilizar recursos iniciales (humanos, financieros y materiales) | C28: 3 | D28: Dominio (3-4) | E28: Emprendimiento (E)
A29: 25 | B29: Reestructurar un proyecto (pivote) ante resultados desfavorables | C29: 3 | D29: Dominio (3-4) | E29: Emprendimiento (E) | F29: =SUM(C25:C29) -> 16 | G29: =IF(F29>=16,"Alto (16-20)",IF(F29>=11,"Medio (11-15)","Bajo (0-10)")) -> Alto (16-20)

Sheet Test 2 - Big Five
A1: EVALUACIÓN DE PERSONALIDAD BIG FIVE (OCEAN) EN ADMINISTRACIÓN (TEST 2)
A2: Escala Likert: 1 = Totalmente en desacuerdo | 2 = En desacuerdo | 3 = Neutral | 4 = De acuerdo | 5 = Totalmente de acuerdo
A4: No. | B4: Dimensión OCEAN / Afirmación Conductual | C4: Puntaje (1-5) | D4: Dimensión OCEAN | E4: Puntaje Bruto (5-25) | F4: % Desarrollo
A5: 1 | B5: Me fascina explorar nuevas ideas, enfoques creativos y tendencias innovadoras | C5: 4 | D5: Apertura a la Experiencia (O)
A6: 2 | B6: Disfruto resolver problemas complejos aprendiendo conceptos completamente nuevos | C6: 4 | D6: Apertura a la Experiencia (O)
A7: 3 | B7: Me adapto fácilmente cuando cambian los planes o el entorno de trabajo | C7: 4 | D7: Apertura a la Experiencia (O)
A8: 4 | B8: Tengo gran curiosidad por comprender la cultura y visión de otras personas | C8: 4 | D8: Apertura a la Experiencia (O)
A9: 5 | B9: Suelo proponer soluciones fuera de lo convencional frente a desafíos | C9: 4 | D9: Apertura a la Experiencia (O) | E9: =SUM(C5:C9) -> 20 | F9: =E9/25 -> 0.8
A10: 6 | B10: Soy meticuloso y cuidadoso al organizar mi tiempo y mis tareas académicas/laborales | C10: 4 | D10: Responsabilidad (C)
A11: 7 | B11: Me aseguro de cumplir mis compromisos con alto nivel de precisión y rigor | C11: 4 | D11: Responsabilidad (C)
A12: 8 | B12: Prefiero seguir planes detallados y estructurados antes de actuar impetuosamente | C12: 3 | D12: Responsabilidad (C)
A13: 9 | B13: Mantengo el enfoque en metas a largo plazo a pesar de las distracciones | C13: 4 | D13: Responsabilidad (C)
A14: 10 | B14: Verifico dos veces la información numérica o documental antes de entregarla | C14: 4 | D14: Responsabilidad (C) | E14: =SUM(C10:C14) -> 19 | F14: =E14/25 -> 0.76
A15: 11 | B15: Me resulta fácil iniciar conversaciones y expresar mis puntos de vista en grupo | C15: 4 | D15: Extraversión (E)
A16: 12 | B16: Disfruto liderar proyectos y motivar a otros hacia el logro de objetivos comunes | C16: 4 | D16: Extraversión (E)
A17: 13 | B17: Me siento lleno de energía cuando trabajo en entornos sociales y dinámicos | C17: 4 | D17: Extraversión (E)
A18: 14 | B18: Tengo facilidad para persuadir y comunicar ideas de forma entusiasta | C18: 4 | D18: Extraversión (E)
A19: 15 | B19: Busco activamente participar en eventos, redes de contacto y trabajo colaborativo | C19: 4 | D19: Extraversión (E) | E19: =SUM(C15:C19) -> 20 | F19: =E19/25 -> 0.8
A20: 16 | B20: Demuestro empatía y comprensión sincera frente a los problemas de los demás | C20: 4 | D20: Amabilidad (A)
A21: 17 | B21: Prefiero colaborar y buscar consensos antes que competir de manera agresiva | C21: 4 | D21: Amabilidad (A)
A22: 18 | B22: Me esfuerzo por mantener relaciones armoniosas y de confianza en el equipo | C22: 4 | D22: Amabilidad (A)
A23: 19 | B23: Escucho activamente las opiniones de otros aun cuando difieran de la mía | C23: 4 | D23: Amabilidad (A)
A24: 20 | B24: Disfruto apoyar el desarrollo personal y profesional de mis compañeros | C24: 4 | D24: Amabilidad (A) | E24: =SUM(C20:C24) -> 20 | F24: =E24/25 -> 0.8
A25: 21 | B25: Mantengo la calma y la claridad mental durante situaciones de alta presión o estrés | C25: 3 | D25: Estabilidad Emocional (N)
A26: 22 | B26: Manejo la frustración de forma serena y busco soluciones sin perder el control | C26: 4 | D26: Estabilidad Emocional (N)
A27: 23 | B27: Tomo decisiones racionales evaluando riesgos en lugar de actuar por impulso emocional | C27: 4 | D27: Estabilidad Emocional (N)
A28: 24 | B28: Recupero rápidamente la confianza frente a imprevistos o resultados negativos | C28: 3 | D28: Estabilidad Emocional (N)
A29: 25 | B29: Transmito tranquilidad y seguridad a mi entorno de trabajo en momentos difíciles | C29: 4 | D29: Estabilidad Emocional (N) | E29: =SUM(C25:C29) -> 18 | F29: =E29/25 -> 0.72

Sheet Guia de Tutoria y Alineacion
A1: GUÍA DE TUTORÍA Y ALINEACIÓN CON MODELOS COMPLEMENTARIOS
A2: Herramienta para el Acompañamiento Académico y Entrevista de Orientación Vocacional (5º Semestre)
A4: Campo Formativo | B4: Perfil Big Five (OCEAN) | C4: Perfil DISC Equivalente | D4: Código Holland (RIASEC) | E4: Dominancia Cerebral (HBDI) | F4: Estrategia de Desarrollo Sugerida
A5: Mercadotecnia | B5: Apertura + Extraversión | C5: I (Influencia) / D (Dominancia) | D5: A (Artístico) / E (Emprendedor) | E5: Amarillo (Creativo / Holístico) | F5: Fortalecer análisis cuantitativo de datos de mercado y métricas ROI.
A6: Capital Humano | B6: Amabilidad + Extraversión | C6: S (Estable) / I (Influencia) | D6: S (Social) / E (Emprendedor) | E6: Rojo (Interpersonal / Emocional) | F6: Desarrollar objetividad analítica para toma de decisiones sobre personal.
A7: Adm. Financiera | B7: Responsabilidad + Estabilidad | C7: C (Conciencia) / D (Dominancia) | D7: C (Convencional) / I (Investigador) | E7: Azul (Analítico / Lógico) | F7: Aumentar flexibilidad cognitiva y habilidades de comunicación ejecutiva.
A8: Negocios Int. | B8: Apertura + Estabilidad + Extraversión | C8: D (Dominancia) / I (Influencia) | D8: E (Emprendedor) / C (Convencional) | E8: Azul / Amarillo (Analítico-Creativo) | F8: Profundizar en idiomas y conocimientos de normatividad aduanera global.
A9: Emprendimiento | B9: Apertura + Responsabilidad + Estabilidad | C9: D (Dominancia) / S (Estable) | D9: E (Emprendedor) / A (Artístico) | E9: Cuadrantes Integrados (Whole Brain) | F9: Fomentar redes de trabajo (networking) y metodologías ágiles (Lean Startup).
A12: PREGUNTAS DETONADORAS PARA LA ENTREVISTA TUTORIAL:
A13: 1. ¿Los resultados reflejados en la 1ª opción coinciden con tus expectativas personales y metas profesionales?
A14: 2. En el campo formativo donde obtuviste mayor puntaje de personalidad pero menor de habilidad, ¿qué asignaturas de 6º a 8º semestre te ayudarán a cerrar esa brecha?
A15: 3. ¿De qué manera tus fortalezas de personalidad (ej. alta responsabilidad o extraversión) te han ayudado a superar proyectos complejos en semestres anteriores?
A16: 4. Si tu 1ª opción requiere habilidades cuantitativas o de negociación que actualmente consideras un desafío, ¿qué plan de acción práctico establecerás este semestre?
